deep_tabular/__init__.py
deep_tabular/embeddings/__init__.py
deep_tabular/embeddings/embedding_factory.py
deep_tabular/embeddings/embedding_utils.py
deep_tabular/models/__init__.py
deep_tabular/models/attention_factory.py
deep_tabular/models/base_model.py
deep_tabular/models/fttransformer.py
deep_tabular/models/mlp.py
deep_tabular/models/model_utils.py
deep_tabular/training/__init__.py
deep_tabular/training/configs.py
deep_tabular/training/dataset.py
deep_tabular/training/encoder.py
deep_tabular/training/initializers.py
deep_tabular/training/losses.py
deep_tabular/training/model_builder.py
deep_tabular/training/trainer.py
deep_tabular/training/training_utils.py
DeepTabularModels-0.1.0.dist-info/LICENSE
DeepTabularModels-0.1.0.dist-info/METADATA
DeepTabularModels-0.1.0.dist-info/WHEEL
DeepTabularModels-0.1.0.dist-info/top_level.txt
DeepTabularModels-0.1.0.dist-info/RECORD
