Metadata-Version: 2.1
Name: DeepTabularModels
Version: 0.1.0
Summary: Deep learning for tabular data
Home-page: https://github.com/AliHaiderAhmad001/deep-tabular.git
Author: Ali Haidar Ahmad
Author-email: ali.h.ahmad001@gmail.com
Classifier: Programming Language :: Python :: 3
Classifier: License :: OSI Approved :: MIT License
Classifier: Operating System :: OS Independent
Requires-Python: >=3.6
License-File: LICENSE
